odoo/addons/partner_time_to_pay/README.rst
odoo/addons/partner_time_to_pay/__init__.py
odoo/addons/partner_time_to_pay/__manifest__.py
odoo/addons/partner_time_to_pay/i18n/es.po
odoo/addons/partner_time_to_pay/i18n/fr.po
odoo/addons/partner_time_to_pay/i18n/gl.po
odoo/addons/partner_time_to_pay/i18n/nl_NL.po
odoo/addons/partner_time_to_pay/i18n/partner_time_to_pay.pot
odoo/addons/partner_time_to_pay/models/__init__.py
odoo/addons/partner_time_to_pay/models/res_partner.py
odoo/addons/partner_time_to_pay/readme/CONTRIBUTORS.rst
odoo/addons/partner_time_to_pay/readme/CREDITS.rst
odoo/addons/partner_time_to_pay/readme/DESCRIPTION.rst
odoo/addons/partner_time_to_pay/readme/INSTALL.rst
odoo/addons/partner_time_to_pay/readme/ROADMAP.rst
odoo/addons/partner_time_to_pay/readme/USAGE.rst
odoo/addons/partner_time_to_pay/static/description/icon.png
odoo/addons/partner_time_to_pay/static/description/index.html
odoo/addons/partner_time_to_pay/views/res_partner.xml
odoo11_addon_partner_time_to_pay-11.0.1.0.0.99.dev10.dist-info/METADATA
odoo11_addon_partner_time_to_pay-11.0.1.0.0.99.dev10.dist-info/WHEEL
odoo11_addon_partner_time_to_pay-11.0.1.0.0.99.dev10.dist-info/top_level.txt
odoo11_addon_partner_time_to_pay-11.0.1.0.0.99.dev10.dist-info/RECORD
